calc_files_control_sum/__init__.py
calc_files_control_sum/cfcs.py
calc_files_control_sum/config.py
calc_files_control_sum/internationalization.py
calc_files_control_sum/my_strings.py
calc_files_control_sum/my_utils.py
calc_files_control_sum/str_without_trans.py
calc_files_control_sum/translated.csv
calc_files_control_sum-1.1.4.dist-info/LICENSE
calc_files_control_sum-1.1.4.dist-info/METADATA
calc_files_control_sum-1.1.4.dist-info/WHEEL
calc_files_control_sum-1.1.4.dist-info/entry_points.txt
calc_files_control_sum-1.1.4.dist-info/top_level.txt
calc_files_control_sum-1.1.4.dist-info/RECORD
