Metadata-Version: 2.1
Name: calc-files-control-sum
Version: 1.1.4
Summary: Calculate files control sum
Home-page: https://github.com/octaprog7/CalcFilesControlSum
Author: Roman Shevchik
Author-email: kolbasilyvasily@yandex.ru
Classifier: Programming Language :: Python :: 3
Classifier: License :: OSI Approved :: MIT License
Classifier: Operating System :: OS Independent
Classifier: Development Status :: 5 - Production/Stable
Classifier: Environment :: Console
Classifier: Intended Audience :: End Users/Desktop
Classifier: Intended Audience :: Developers
Classifier: Intended Audience :: System Administrators
Requires-Python: >=3.7.2,<3.12
License-File: LICENSE
